{
  "cli": {
    "version": ">= 16.1.0",
    "appVersionSource": "remote"
  },
  "build": {
    "development": {
      "developmentClient": true,
      "distribution": "internal",
      "android": {
        "buildType": "apk"
      },
      "env": {
        "ENV": "development"
      }
    },
    "preview": {
      "distribution": "internal",
      "android": {
        "buildType": "apk"
      },
      "env": {
        "ENV": "preview"
      }
    },
    "production": {
      "autoIncrement": true,
      "android": {
        "buildType": "app-bundle"
      },
      "ios": {
        "simulator": false
      },
      "env": {
        "ENV": "production"
      }
    }
  },
  "submit": {
    "production": {}
  }
}
